rust_silence/__init__.py
rust_silence/_rust_silence.cpython-313-x86_64-linux-musl.so
rust_silence/core.py
rust_silence.libs/libgcc_s-2298274a.so.1
rust_silence-0.1.2.dist-info/METADATA
rust_silence-0.1.2.dist-info/WHEEL
rust_silence-0.1.2.dist-info/top_level.txt
rust_silence-0.1.2.dist-info/RECORD
rust_silence-0.1.2.dist-info/licenses/LICENSE
