Metadata-Version: 2.4
Name: rust_silence
Version: 0.1.2
Author: Rungrod Thongjampa
Author-email: rungrodks@hotmail.com
License: MIT License
Project-URL: homepage, https://github.com/ccyrene/rust_silence
Project-URL: repository, https://github.com/ccyrene/rust_silence
Requires-Python: >=3.10
License-File: LICENSE
Dynamic: license-file
